MANIFEST.in
README.md
examples_requirements.txt
requirements.txt
setup.py
spm_image.egg-info/PKG-INFO
spm_image.egg-info/SOURCES.txt
spm_image.egg-info/dependency_links.txt
spm_image.egg-info/requires.txt
spm_image.egg-info/top_level.txt
spmimage/__init__.py
spmimage/decomposition/__init__.py
spmimage/decomposition/dct.py
spmimage/decomposition/dict_learning.py
spmimage/decomposition/ksvd.py
spmimage/experimental/__init__.py
spmimage/experimental/enable_ppd.py
spmimage/feature_extraction/__init__.py
spmimage/feature_extraction/image.py
spmimage/linear_model/__init__.py
spmimage/linear_model/_ppd.py
spmimage/linear_model/admm.py
spmimage/linear_model/hmlasso.py
spmimage/preprocessing/__init__.py
spmimage/preprocessing/data.py
tests/__init__.py
tests/test_decomposition_dct.py
tests/test_decomposition_dict_learning.py
tests/test_decomposition_ksvd.py
tests/test_experimental.py
tests/test_feature_extraction_image.py
tests/test_linear_model_admm.py
tests/test_linear_model_hmlasso.py
tests/test_linear_model_ppd.py
tests/test_notebook.py
tests/test_preprocessing_whitening.py
tests/utils.py