Metadata-Version: 1.0
Name: spm-image
Version: 0.0.11
Summary: Sparse modeling and Compressive sensing in Python
Home-page: https://github.com/hacarus/spm-image
Author: Takashi Someda
Author-email: takashi@hacarus.com
License: Modified BSD
Platform: UNKNOWN
